phylotoast/__init__.py
phylotoast/biom_calc.py
phylotoast/graph_util.py
phylotoast/otu_calc.py
phylotoast/util.py
phylotoast/test/__init__.py
phylotoast/test/test_biom_calc.py
phylotoast/test/test_otu_calc.py
phylotoast/test/test_phylotoast.py
phylotoast/test/test_util.py
phylotoast-1.3.0.data/data/data/pbs_job_template.pbs
phylotoast-1.3.0.data/data/data/slurm_job_template.sbatch
phylotoast-1.3.0.data/scripts/LDA.py
phylotoast-1.3.0.data/scripts/PCoA.py
phylotoast-1.3.0.data/scripts/PCoA_bubble.py
phylotoast-1.3.0.data/scripts/assign_taxonomy_by_blast_result.py
phylotoast-1.3.0.data/scripts/barcode_filter.py
phylotoast-1.3.0.data/scripts/biom_phyla_summary.py
phylotoast-1.3.0.data/scripts/biom_relative_abundance.py
phylotoast-1.3.0.data/scripts/condense_workflow.py
phylotoast-1.3.0.data/scripts/diversity.py
phylotoast-1.3.0.data/scripts/filter_keep_otus_by_sample.py
phylotoast-1.3.0.data/scripts/filter_rep_set.py
phylotoast-1.3.0.data/scripts/iTol.py
phylotoast-1.3.0.data/scripts/merge_otu_results.py
phylotoast-1.3.0.data/scripts/multi_parallel_pick_otus.py
phylotoast-1.3.0.data/scripts/multi_qsub.py
phylotoast-1.3.0.data/scripts/otu_condense.py
phylotoast-1.3.0.data/scripts/otu_to_tax_name.py
phylotoast-1.3.0.data/scripts/pick_otus_condense.py
phylotoast-1.3.0.data/scripts/primer_average.py
phylotoast-1.3.0.data/scripts/prune_otus.py
phylotoast-1.3.0.data/scripts/restrict_repset.py
phylotoast-1.3.0.data/scripts/sanger_qiimify.py
phylotoast-1.3.0.data/scripts/split_sequence_data.py
phylotoast-1.3.0.data/scripts/transpose_biom.py
phylotoast-1.3.0.dist-info/DESCRIPTION.rst
phylotoast-1.3.0.dist-info/METADATA
phylotoast-1.3.0.dist-info/RECORD
phylotoast-1.3.0.dist-info/WHEEL
phylotoast-1.3.0.dist-info/metadata.json
phylotoast-1.3.0.dist-info/top_level.txt
