Metadata-Version: 2.0
Name: phylotoast
Version: 1.3.0
Summary: Useful additions to the QIIME analysis pipeline including tools for data visualization and cluster-computing.
Home-page: https://github.com/smdabdoub/phylotoast
Author: Shareef M. Dabdoub
Author-email: dabdoub.2@osu.edu
License: MIT
Keywords: bioinformatics,QIIME,phylotoast,microbial ecology,16S,microbiology
Platform: UNKNOWN
Classifier: Development Status :: 5 - Production/Stable
Classifier: Environment :: Console
Classifier: Topic :: Scientific/Engineering :: Bio-Informatics
Classifier: Intended Audience :: Science/Research
Classifier: Intended Audience :: Developers
Classifier: Natural Language :: English
Classifier: License :: OSI Approved :: MIT License
Classifier: Programming Language :: Python
Classifier: Programming Language :: Python :: 2.7
Classifier: Operating System :: Unix
Classifier: Operating System :: MacOS :: MacOS X
Classifier: Operating System :: POSIX :: BSD
Classifier: Operating System :: POSIX :: Linux
Classifier: Operating System :: Microsoft :: Windows
